VICAR/vos/p2/inc/cmod_cahvor.h
VICAR/vos/p2/inc/cmod_cahvore.h
VICAR/vos/p2/inc/cmod_cahv.h
VICAR/vos/crumbs/orbital/dem2mesh_mipl_test.py
VICAR/vos/crumbs/orbital/m20_orbital_mesh_gen.py
VICAR/vos/util/canonical_version.py
VICAR/vos/util/build_wars.py
VICAR/vos/util/build_python_projects.py
VICAR/vos/mars/src/prog/slam/slam.py
VICAR/vos/mars/src/prog/slam/slam_config_writer.py
VICAR/vos/mars/src/prog/slam/util/slam_headers2camparams.py
VICAR/vos/mars/src/prog/slam/util/slam_dataframe2params.py
VICAR/vos/mars/src/prog/slam/util/slam_merge_nav.py
VICAR/vos/mars/src/prog/slam/util/slam_run_posegraph.py
VICAR/vos/mars/src/prog/slam/util/slam_nav_dataframe.py
VICAR/vos/mars/src/prog/slam/util/slam_merge_nav_df.py
VICAR/vos/mars/src/prog/slam/util/slam_tie_dataframe.py
tests/test_cahvore.py
tests/__init__.py
cycahvore-0.0.1a0.dist-info/RECORD
cycahvore-0.0.1a0.dist-info/LICENSE
cycahvore-0.0.1a0.dist-info/WHEEL
cycahvore-0.0.1a0.dist-info/top_level.txt
cycahvore-0.0.1a0.dist-info/METADATA
cycahvore/__init__.py
cycahvore/cahv.cpython-311-darwin.so
cycahvore/cahvor.cpython-311-darwin.so
cycahvore/cahvore.cpython-311-darwin.so
