Metadata-Version: 2.1
Name: cycahvore
Version: 0.0.1a0
Summary: Cython wrapper for CAHVORE camera models
Author-email: "Dr. Andrew Annex" <ama6fy@virginia.edu>
License: Apache License
Project-URL: Repository, https://github.com/AndrewAnnex/cycahvore.git
Keywords: Cython,camera model,CAHVORE,CAHVOR,CAHV
Classifier: Development Status :: 3 - Alpha
Classifier: Programming Language :: Cython
Classifier: Programming Language :: Python :: 3.10
Classifier: Programming Language :: Python :: 3.11
Classifier: Programming Language :: Python :: 3.12
Classifier: Intended Audience :: Science/Research
Classifier: Topic :: Scientific/Engineering
Classifier: Topic :: Scientific/Engineering :: Astronomy
Classifier: Topic :: Scientific/Engineering :: GIS
Classifier: Topic :: Scientific/Engineering :: Visualization
Requires-Python: >=3.10
License-File: LICENSE
Requires-Dist: cython
Requires-Dist: numpy
Requires-Dist: pytest
